alu.v
module alu(
    input [7:0] A,
    input [7:0] B,
    input [3:0] opcode,
    output reg [7:0] result
);

always @(*) begin
    case(opcode)

        4'b0000: result = A + B;          // Addition
        4'b0001: result = A - B;          // Subtraction
        4'b0010: result = A & B;          // AND
        4'b0011: result = A | B;          // OR
        4'b0100: result = A ^ B;          // XOR
        4'b0101: result = A << 1;         // Left Shift
        4'b0110: result = A >> 1;         // Right Shift
        4'b0111: result = (A == B) ? 8'd1 : 8'd0; // Compare

        default: result = 8'd0;

    endcase
end

endmodule

alu_tb.v
`timescale 1ns/1ps

module alu_tb;

reg [7:0] A;
reg [7:0] B;
reg [3:0] opcode;

wire [7:0] result;

alu uut (
    .A(A),
    .B(B),
    .opcode(opcode),
    .result(result)
);

initial begin

    // Generate waveform file
    $dumpfile("dump.vcd");
    $dumpvars(0, alu_tb);

    // Test Values
    A = 8'd10;
    B = 8'd5;

    // Addition
    opcode = 4'b0000;
    #10;

    // Subtraction
    opcode = 4'b0001;
    #10;

    // AND
    opcode = 4'b0010;
    #10;

    // OR
    opcode = 4'b0011;
    #10;

    // XOR
    opcode = 4'b0100;
    #10;

    // Left Shift
    opcode = 4'b0101;
    #10;

    // Right Shift
    opcode = 4'b0110;
    #10;

    // Comparison
    opcode = 4'b0111;
    #10;

    $finish;

end

endmodule

dump.vcd
$date
	Mon Jun 01 13:21:02 2026
$end
$version
	Icarus Verilog
$end
$timescale
	1ps
$end
$scope module alu_tb $end
$var wire 8 ! result [7:0] $end
$var reg 8 " A [7:0] $end
$var reg 8 # B [7:0] $end
$var reg 4 $ opcode [3:0] $end
$scope module uut $end
$var wire 8 % A [7:0] $end
$var wire 8 & B [7:0] $end
$var wire 4 ' opcode [3:0] $end
$var reg 8 ( result [7:0] $end
$upscope $end
$upscope $end
$enddefinitions $end
$comment Show the parameter values. $end
$dumpall
$end
#0
$dumpvars
b1111 (
b0 '
b101 &
b1010 %
b0 $
b101 #
b1010 "
b1111 !
$end
#10000
b101 !
b101 (
b1 $
b1 '
#20000
b0 !
b0 (
b10 $
b10 '
#30000
b1111 !
b1111 (
b11 $
b11 '
#40000
b100 $
b100 '
#50000
b10100 !
b10100 (
b101 $
b101 '
#60000
b101 !
b101 (
b110 $
b110 '
#70000
b0 !
b0 (
b111 $
b111 '
